{"runtime":120,"status":"Released","backdrop_path":"\/3axPBC6p8rNt82qbJHOC0B1SlDj.jpg","overview":"Au siècle dernier en Nouvelle-Zelande, Ada, mère d'une fillette de neuf ans, s'apprète à suivre son nouveau mari au fin fond du bush. Il accepte de transporter tous ses meubles à l'exception d'un piano qui échoue chez un voisin illettré. Ne pouvant supporter cette perte, Ada accepte le marché que lui propose ce dernier. Regagner son piano touche par touche en se soumettant à ses fantaisies. Palme d'or et prix d'interprétation féminine à Cannes en 1993.","title":"La Leçon de piano","vote_count":1208,"tagline":"","belongs_to_collection":null,"original_title":"The Piano","original_language":"en","poster_path":"\/wyQO9ugIqj6mB8v7dwPJZOYijV4.jpg","production_countries":[{"name":"New Zealand","iso_3166_1":"NZ"},{"name":"Australia","iso_3166_1":"AU"},{"name":"France","iso_3166_1":"FR"}],"revenue":40185556,"homepage":"","video":false,"imdb_id":"tt0107822","id":713,"release_date":"1993-05-19","budget":7000000,"popularity":15.000999999999999,"genres":[{"id":18,"name":"Drame"},{"id":10749,"name":"Romance"}],"production_companies":[{"logo_path":"\/pyiNvPJYGz4W2SImgULoG2sn4y4.png","id":105,"origin_country":"FR","name":"CiBy 2000"},{"logo_path":"\/w7d3hoHQaC0XwjrxEG1yPeuUhu5.png","id":417,"origin_country":"AU","name":"Australian Film Commission"},{"logo_path":null,"id":418,"origin_country":"AU","name":"New South Wales Film & Television Office"},{"logo_path":null,"id":14089,"origin_country":"","name":"Jan Chapman Productions"}],"adult":false,"spoken_languages":[{"english_name":"English","name":"English","iso_639_1":"en"},{"english_name":"Maori","name":"","iso_639_1":"mi"}],"vote_average":7.4029999999999996}