{"runtime":124,"status":"Released","backdrop_path":"\/75nSb1fbWooipwcSU5bUttiOriI.jpg","overview":"Après la disparition de sa mère dans un incendie, Mahito, un jeune garçon de 11 ans, doit quitter Tokyo pour partir vivre à la campagne dans le village où elle a grandi. Il s’installe avec son père dans un vieux manoir situé sur un immense domaine où il rencontre un héron cendré qui devient petit à petit son guide et l’aide au fil de ses découvertes et questionnements à comprendre le monde qui l'entoure et percer les mystères de la vie.","title":"Le Garçon et le héron","vote_count":1858,"tagline":"Là où la mort prend fin, la vie trouve un nouveau commencement.","belongs_to_collection":null,"original_title":"君たちはどう生きるか","original_language":"ja","poster_path":"\/f9EoS3lVr644WXO8YPRvBiTS1K.jpg","origin_country":["JP"],"production_countries":[{"name":"Japan","iso_3166_1":"JP"}],"homepage":"","revenue":294200000,"imdb_id":"tt6587046","video":false,"id":508883,"release_date":"2023-07-14","budget":50000000,"popularity":85.793000000000006,"genres":[{"id":16,"name":"Animation"},{"id":12,"name":"Aventure"},{"id":14,"name":"Fantastique"},{"id":10751,"name":"Familial"},{"id":18,"name":"Drame"}],"production_companies":[{"logo_path":"\/eS79pslnoKbWg7t3PMA9ayl0bGs.png","id":10342,"origin_country":"JP","name":"Studio Ghibli"}],"adult":false,"spoken_languages":[{"english_name":"Japanese","name":"日本語","iso_639_1":"ja"}],"vote_average":7.5}