{"crew":[{"gender":1,"original_name":"Reese Witherspoon","total_episode_count":8,"id":368,"adult":false,"known_for_department":"Acting","popularity":31.556000000000001,"jobs":[{"credit_id":"60ca67d54f3a4c0057c7988b","job":"Executive Producer","episode_count":8}],"department":"Production","profile_path":"\/odkbrsn8I9m0zIVSntrDTl3hjUh.jpg","name":"Reese Witherspoon"},{"gender":0,"original_name":"Veronica West","total_episode_count":8,"id":1215696,"adult":false,"known_for_department":"Writing","popularity":1.5600000000000001,"jobs":[{"credit_id":"60ca67bd42d8a5003f7ac19f","job":"Executive Producer","episode_count":8}],"department":"Production","profile_path":null,"name":"Veronica West"},{"gender":1,"original_name":"Gugu Mbatha-Raw","total_episode_count":8,"id":1216606,"adult":false,"known_for_department":"Acting","popularity":11.026999999999999,"jobs":[{"credit_id":"60ca6826f12cf4002933f800","job":"Executive Producer","episode_count":8}],"department":"Production","profile_path":"\/6QInv8etQHXTbiMkJTzftvJ40RP.jpg","name":"Gugu Mbatha-Raw"},{"gender":2,"original_name":"Jon Wu","total_episode_count":8,"id":3127133,"adult":false,"known_for_department":"Production","popularity":0.59999999999999998,"jobs":[{"credit_id":"60ca686666ae4d007af0470e","job":"Producer","episode_count":8}],"department":"Production","profile_path":null,"name":"Jon Wu"},{"gender":0,"original_name":"Ashley Strumwasser","total_episode_count":8,"id":2702883,"adult":false,"known_for_department":"Acting","popularity":0.59999999999999998,"jobs":[{"credit_id":"60ca685d7739410057897f5e","job":"Producer","episode_count":8}],"department":"Production","profile_path":null,"name":"Ashley Strumwasser"},{"gender":1,"original_name":"Lauren Neustadter","total_episode_count":8,"id":2059513,"adult":false,"known_for_department":"Production","popularity":0.83999999999999997,"jobs":[{"credit_id":"60ca67de18864b002977c6c6","job":"Executive Producer","episode_count":8}],"department":"Production","profile_path":null,"name":"Lauren Neustadter"},{"gender":0,"original_name":"Veronica West","total_episode_count":1,"id":1215696,"adult":false,"known_for_department":"Writing","popularity":1.5600000000000001,"jobs":[{"credit_id":"60ca67f517c4430040884990","job":"Writer","episode_count":1}],"department":"Writing","profile_path":null,"name":"Veronica West"}],"cast":[{"gender":1,"original_name":"Gugu Mbatha-Raw","roles":[{"credit_id":"60ca68cf12197e006e504597","character":"Sophie Ellis","episode_count":8}],"id":1216606,"adult":false,"known_for_department":"Acting","popularity":11.026999999999999,"order":0,"profile_path":"\/6QInv8etQHXTbiMkJTzftvJ40RP.jpg","name":"Gugu Mbatha-Raw","total_episode_count":8},{"gender":2,"original_name":"Oliver Jackson-Cohen","roles":[{"credit_id":"60ca68d72fccee00780a7501","character":"James Ellis","episode_count":8}],"id":551020,"adult":false,"known_for_department":"Acting","popularity":8.2609999999999992,"order":1,"profile_path":"\/hya4m356KlAeH6qaCLGm1Sg02xf.jpg","name":"Oliver Jackson-Cohen","total_episode_count":8},{"gender":1,"original_name":"Ari Graynor","roles":[{"credit_id":"60ca68f918864b00588af871","character":"Caroline","episode_count":8}],"id":71552,"adult":false,"known_for_department":"Acting","popularity":3.8860000000000001,"order":2,"profile_path":"\/5zeItxS6KlT6SzOJnsRZEzCv0Mm.jpg","name":"Ari Graynor","total_episode_count":8},{"gender":2,"original_name":"François Arnaud","roles":[{"credit_id":"60ca690c66ae4d00420fd3ba","character":"Harrison","episode_count":8}],"id":469462,"adult":false,"known_for_department":"Acting","popularity":6.6379999999999999,"order":3,"profile_path":"\/ftRBKhV73YQ8UOT2gUcG9P1m1zB.jpg","name":"François Arnaud","total_episode_count":8},{"gender":1,"original_name":"Millie Brady","roles":[{"credit_id":"60ca692877394100277942cf","character":"Eliza","episode_count":8}],"id":1460120,"adult":false,"known_for_department":"Acting","popularity":16.516999999999999,"order":4,"profile_path":"\/8IBIRaUl4QyttlieUfKVBR2Ia5J.jpg","name":"Millie Brady","total_episode_count":8},{"gender":1,"original_name":"Marianne Jean-Baptiste","roles":[{"credit_id":"60ca691c17c443006e896004","character":"Hannah","episode_count":8}],"id":17352,"adult":false,"known_for_department":"Acting","popularity":5.1589999999999998,"order":5,"profile_path":"\/ggAAGN9ei8hggTwDVO4sjZpIS6t.jpg","name":"Marianne Jean-Baptiste","total_episode_count":8},{"gender":2,"original_name":"Stephan James","roles":[{"credit_id":"60ca68ec12197e003f6bf575","character":"Thomas Baden","episode_count":8}],"id":1388314,"adult":false,"known_for_department":"Acting","popularity":4.7789999999999999,"order":6,"profile_path":"\/i3dx4BvgRh4maR03R4rdsgGexlV.jpg","name":"Stephan James","total_episode_count":8}],"id":127641}