{"crew":[{"gender":1,"original_name":"Rosie Clarke","total_episode_count":12,"id":1293421,"adult":false,"known_for_department":"Art","popularity":0.59999999999999998,"jobs":[{"credit_id":"5b7fae23c3a3687e1600973d","job":"Art Direction","episode_count":12}],"department":"Art","profile_path":null,"name":"Rosie Clarke"},{"gender":1,"original_name":"Luana Hanson","total_episode_count":12,"id":1602647,"adult":false,"known_for_department":"Art","popularity":0.59999999999999998,"jobs":[{"credit_id":"5b7fadf79251416c890087cd","job":"Production Design","episode_count":12}],"department":"Art","profile_path":null,"name":"Luana Hanson"},{"gender":0,"original_name":"Bex Harvey","total_episode_count":1,"id":1713235,"adult":false,"known_for_department":"Writing","popularity":0.59999999999999998,"jobs":[{"credit_id":"5dd87cdc3faba00019fa2868","job":"Art Direction","episode_count":1}],"department":"Art","profile_path":null,"name":"Bex Harvey"},{"gender":2,"original_name":"Jamie Cairney","total_episode_count":12,"id":1674573,"adult":false,"known_for_department":"Camera","popularity":0.59999999999999998,"jobs":[{"credit_id":"5dd87e480cd446001225c915","job":"Director of Photography","episode_count":12}],"department":"Camera","profile_path":null,"name":"Jamie Cairney"},{"gender":2,"original_name":"Sam Perry","total_episode_count":12,"id":1706568,"adult":false,"known_for_department":"Costume & Make-Up","popularity":1.3799999999999999,"jobs":[{"credit_id":"5dd87def0cd446001225c86d","job":"Costume Designer","episode_count":12}],"department":"Costume & Make-Up","profile_path":null,"name":"Sam Perry"},{"gender":0,"original_name":"Kate Gill","total_episode_count":6,"id":2060696,"adult":false,"known_for_department":"Costume & Make-Up","popularity":0.59999999999999998,"jobs":[{"credit_id":"5dd87d2d0cd446001425c4ba","job":"Assistant Costume Designer","episode_count":6}],"department":"Costume & Make-Up","profile_path":null,"name":"Kate Gill"},{"gender":0,"original_name":"Laura Venables","total_episode_count":6,"id":1706574,"adult":false,"known_for_department":"Costume & Make-Up","popularity":0.59999999999999998,"jobs":[{"credit_id":"5dd87d3d0cd446001425c4ec","job":"Wardrobe Supervisor","episode_count":6}],"department":"Costume & Make-Up","profile_path":null,"name":"Laura Venables"},{"gender":0,"original_name":"Nerys Evans","total_episode_count":6,"id":2114091,"adult":false,"known_for_department":"Crew","popularity":0.59999999999999998,"jobs":[{"credit_id":"5b7fac800e0a2660a80091a0","job":"Commissioning Editor","episode_count":6}],"department":"Crew","profile_path":null,"name":"Nerys Evans"},{"gender":0,"original_name":"Tanya Qureshi","total_episode_count":6,"id":2114096,"adult":false,"known_for_department":"Crew","popularity":0.59999999999999998,"jobs":[{"credit_id":"5b7face40e0a2660a80091e3","job":"Commissioning Editor","episode_count":6}],"department":"Crew","profile_path":null,"name":"Tanya Qureshi"},{"gender":2,"original_name":"Will Sharpe","total_episode_count":12,"id":939337,"adult":false,"known_for_department":"Acting","popularity":5.9669999999999996,"jobs":[{"credit_id":"5dd87af312aabc00168f8000","job":"Director","episode_count":12}],"department":"Directing","profile_path":"\/u1r07jbgeObrIDixZljdS88llUG.jpg","name":"Will Sharpe"},{"gender":0,"original_name":"Arizona Eastwood","total_episode_count":1,"id":2069437,"adult":false,"known_for_department":"Directing","popularity":0.59999999999999998,"jobs":[{"credit_id":"5dd87cb43faba00019fa27dd","job":"Third Assistant Director","episode_count":1}],"department":"Directing","profile_path":null,"name":"Arizona Eastwood"},{"gender":0,"original_name":"Alex Streeter","total_episode_count":1,"id":2309183,"adult":false,"known_for_department":"Directing","popularity":0.59999999999999998,"jobs":[{"credit_id":"5dd87c973faba00019fa278c","job":"First Assistant Director","episode_count":1}],"department":"Directing","profile_path":null,"name":"Alex Streeter"},{"gender":0,"original_name":"Selina Macarthur","total_episode_count":12,"id":1533577,"adult":false,"known_for_department":"Editing","popularity":0.59999999999999998,"jobs":[{"credit_id":"5b7faeb20e0a26609a00a2ff","job":"Editor","episode_count":12}],"department":"Editing","profile_path":null,"name":"Selina Macarthur"},{"gender":0,"original_name":"Naomi De Pear","total_episode_count":12,"id":2114088,"adult":false,"known_for_department":"Production","popularity":1.6140000000000001,"jobs":[{"credit_id":"5b7faabb9251416c80008285","job":"Executive Producer","episode_count":12}],"department":"Production","profile_path":"\/gP7ohe7cMM6buCwpjl4ZmVAIuIp.jpg","name":"Naomi De Pear"},{"gender":0,"original_name":"Catherine Willis","total_episode_count":12,"id":1431135,"adult":false,"known_for_department":"Production","popularity":0.59999999999999998,"jobs":[{"credit_id":"5dd87d9012aabc00168f85f6","job":"Casting Director","episode_count":12}],"department":"Production","profile_path":null,"name":"Catherine Willis"},{"gender":0,"original_name":"Holly Pullinger","total_episode_count":12,"id":2114089,"adult":false,"known_for_department":"Production","popularity":0.59999999999999998,"jobs":[{"credit_id":"5b7faae09251416c97008105","job":"Line Producer","episode_count":12}],"department":"Production","profile_path":null,"name":"Holly Pullinger"},{"gender":0,"original_name":"Diederick Santer","total_episode_count":6,"id":1227795,"adult":false,"known_for_department":"Production","popularity":0.59999999999999998,"jobs":[{"credit_id":"5b7facb89251416c840096bf","job":"Executive Producer","episode_count":6}],"department":"Production","profile_path":null,"name":"Diederick Santer"},{"gender":1,"original_name":"Jane Featherstone","total_episode_count":6,"id":125248,"adult":false,"known_for_department":"Production","popularity":0.65000000000000002,"jobs":[{"credit_id":"5dd87e6def8b3200148c5375","job":"Executive Producer","episode_count":6}],"department":"Production","profile_path":"\/jYdEOebFggHs4sxg36BpXNAaAMb.jpg","name":"Jane Featherstone"},{"gender":2,"original_name":"Will Sharpe","total_episode_count":6,"id":939337,"adult":false,"known_for_department":"Acting","popularity":5.9669999999999996,"jobs":[{"credit_id":"5b7fad0cc3a3687e1300869f","job":"Associate Producer","episode_count":6}],"department":"Production","profile_path":"\/u1r07jbgeObrIDixZljdS88llUG.jpg","name":"Will Sharpe"},{"gender":0,"original_name":"Emma Kingsman-Lloyd","total_episode_count":6,"id":1554223,"adult":false,"known_for_department":"Production","popularity":0.59999999999999998,"jobs":[{"credit_id":"5dd87e890cd446001425c917","job":"Producer","episode_count":6}],"department":"Production","profile_path":null,"name":"Emma Kingsman-Lloyd"},{"gender":0,"original_name":"Sam Pinnell","total_episode_count":6,"id":84742,"adult":false,"known_for_department":"Production","popularity":0.59999999999999998,"jobs":[{"credit_id":"5b7facd0c3a3687e1900939f","job":"Producer","episode_count":6}],"department":"Production","profile_path":null,"name":"Sam Pinnell"},{"gender":0,"original_name":"Arthur Sharpe","total_episode_count":12,"id":1928502,"adult":false,"known_for_department":"Sound","popularity":0.59999999999999998,"jobs":[{"credit_id":"5b7faa7a9251416c8e008a24","job":"Original Music Composer","episode_count":12}],"department":"Sound","profile_path":null,"name":"Arthur Sharpe"},{"gender":2,"original_name":"Will Sharpe","total_episode_count":12,"id":939337,"adult":false,"known_for_department":"Acting","popularity":5.9669999999999996,"jobs":[{"credit_id":"5dd87aeab5bc210016c4c12c","job":"Writer","episode_count":12}],"department":"Writing","profile_path":"\/u1r07jbgeObrIDixZljdS88llUG.jpg","name":"Will Sharpe"}],"cast":[{"gender":1,"original_name":"Olivia Colman","roles":[{"credit_id":"570f9eeec3a36860a80013f8","character":"Deborah Flowers","episode_count":12}],"id":39187,"adult":false,"known_for_department":"Acting","popularity":22.309999999999999,"order":0,"profile_path":"\/4ZwZ66zXZyX26Kf2wfeMt1tQZQf.jpg","name":"Olivia Colman","total_episode_count":12},{"gender":2,"original_name":"Julian Barratt","roles":[{"credit_id":"570f9f08c3a3685373002d6b","character":"Maurice Flowers","episode_count":12}],"id":98104,"adult":false,"known_for_department":"Acting","popularity":6.8840000000000003,"order":1,"profile_path":"\/ltwOEsHkes9oCgy9Dl95q8nMyUT.jpg","name":"Julian Barratt","total_episode_count":12},{"gender":1,"original_name":"Sophia Di Martino","roles":[{"credit_id":"570f9f31c3a36860a8001405","character":"Amy Flowers","episode_count":12}],"id":1252533,"adult":false,"known_for_department":"Acting","popularity":8.4760000000000009,"order":2,"profile_path":"\/qZdFp18btpQJfDoknxr7DgfRpcB.jpg","name":"Sophia Di Martino","total_episode_count":12},{"gender":2,"original_name":"Daniel Rigby","roles":[{"credit_id":"570f9f1d9251416d95000126","character":"Donald Flowers","episode_count":12}],"id":211368,"adult":false,"known_for_department":"Acting","popularity":1.5940000000000001,"order":3,"profile_path":"\/5G6E2ziY1AeYJ9Ud7ZS6nwvisAE.jpg","name":"Daniel Rigby","total_episode_count":12},{"gender":2,"original_name":"Will Sharpe","roles":[{"credit_id":"570f9f4492514133f3001660","character":"Shun","episode_count":12}],"id":939337,"adult":false,"known_for_department":"Acting","popularity":5.9669999999999996,"order":4,"profile_path":"\/u1r07jbgeObrIDixZljdS88llUG.jpg","name":"Will Sharpe","total_episode_count":12},{"gender":1,"original_name":"Anna Chancellor","roles":[{"credit_id":"570faec4925141016f002202","character":"Viv","episode_count":12}],"id":10731,"adult":false,"known_for_department":"Acting","popularity":18.350000000000001,"order":7,"profile_path":"\/gKU8hHdC45q9WpYy4SeNLEhPwtK.jpg","name":"Anna Chancellor","total_episode_count":12},{"gender":0,"original_name":"Rico Canadinhas","roles":[{"credit_id":"570fae1c9251416d730003a3","character":"Hugo","episode_count":12}],"id":1605764,"adult":false,"known_for_department":"Acting","popularity":0.59999999999999998,"order":8,"profile_path":null,"name":"Rico Canadinhas","total_episode_count":12},{"gender":2,"original_name":"Alistair Green","roles":[{"credit_id":"570fae3492514108320000cc","character":"Tommy","episode_count":12}],"id":1605765,"adult":false,"known_for_department":"Acting","popularity":1.1759999999999999,"order":9,"profile_path":"\/oSB7By69vVaq9TQQXiLMEHmHC9k.jpg","name":"Alistair Green","total_episode_count":12},{"gender":1,"original_name":"Zita Sattar","roles":[{"credit_id":"570fadfd92514108320000bf","character":"Barbara","episode_count":12}],"id":1234987,"adult":false,"known_for_department":"Acting","popularity":0.74299999999999999,"order":10,"profile_path":"\/fCBkNJplXGxUxZLeOPRMOnlms1k.jpg","name":"Zita Sattar","total_episode_count":12},{"gender":2,"original_name":"Angus Wright","roles":[{"credit_id":"570faddac3a3685373002f4c","character":"George","episode_count":12}],"id":933640,"adult":false,"known_for_department":"Acting","popularity":4.3620000000000001,"order":11,"profile_path":"\/7VOW55b8WF0eyFJiCjiBXSRA5mG.jpg","name":"Angus Wright","total_episode_count":12},{"gender":2,"original_name":"Colin Hurley","roles":[{"credit_id":"570fadeb92514108320000bc","character":"Barry","episode_count":12}],"id":1340970,"adult":false,"known_for_department":"Acting","popularity":0.59999999999999998,"order":12,"profile_path":"\/4ovei6hO3uyOVTwM3uh2I29igZ8.jpg","name":"Colin Hurley","total_episode_count":12},{"gender":2,"original_name":"Hammed Animashaun","roles":[{"credit_id":"570fae469251416a56001118","character":"Ryan","episode_count":12}],"id":1208302,"adult":false,"known_for_department":"Acting","popularity":2.0369999999999999,"order":13,"profile_path":"\/7vixuZd37cqAWFfZ5YLhc48QYyE.jpg","name":"Hammed Animashaun","total_episode_count":12},{"gender":1,"original_name":"Desiree Akhavan","roles":[{"credit_id":"570fae52c3a368503c0019cb","character":"Carol","episode_count":12}],"id":1285174,"adult":false,"known_for_department":"Acting","popularity":3.927,"order":14,"profile_path":"\/xus5HH2qSyrP5SNK6516LVajg6.jpg","name":"Desiree Akhavan","total_episode_count":12},{"gender":0,"original_name":"Helen Cripps","roles":[{"credit_id":"570fae64c3a3685378003141","character":"Matilda","episode_count":12}],"id":1598279,"adult":false,"known_for_department":"Acting","popularity":0.59999999999999998,"order":15,"profile_path":"\/aeb2uCCp8YiY04P3lSSegufDt7C.jpg","name":"Helen Cripps","total_episode_count":12},{"gender":0,"original_name":"Sharon Young","roles":[{"credit_id":"570fae759251416a56001120","character":"Dr Grey","episode_count":12}],"id":1414111,"adult":false,"known_for_department":"Acting","popularity":0.59999999999999998,"order":16,"profile_path":null,"name":"Sharon Young","total_episode_count":12},{"gender":1,"original_name":"Leila Hoffman","roles":[{"credit_id":"570f9f639251413a9200062c","character":"Nana","episode_count":6}],"id":430776,"adult":false,"known_for_department":"Acting","popularity":1.7569999999999999,"order":5,"profile_path":"\/eI2eL9s2VVMVfmie7xO7jeDcLiM.jpg","name":"Leila Hoffman","total_episode_count":6},{"gender":1,"original_name":"Georgina Campbell","roles":[{"credit_id":"570fadc8925141016f0021dc","character":"Abigail","episode_count":6}],"id":1335315,"adult":false,"known_for_department":"Acting","popularity":7.4560000000000004,"order":6,"profile_path":"\/AwFvnApH8nxzfEw3inQw7Dvc0qq.jpg","name":"Georgina Campbell","total_episode_count":6},{"gender":1,"original_name":"Maite Jáuregui","roles":[{"credit_id":"5be1c69e9251414df4010aa0","character":"Vera","episode_count":6}],"id":1488249,"adult":false,"known_for_department":"Acting","popularity":0.59999999999999998,"order":17,"profile_path":"\/3wHwoj1ZyIIGNPlHCozAcjWFUNl.jpg","name":"Maite Jáuregui","total_episode_count":6},{"gender":2,"original_name":"Duncan Pow","roles":[{"credit_id":"5b447f399251414f5c028258","character":"Dennis","episode_count":2}],"id":1264237,"adult":false,"known_for_department":"Acting","popularity":1.3999999999999999,"order":500,"profile_path":"\/sRXFbRCHuvKdeV8RZX7fQwjcuf0.jpg","name":"Duncan Pow","total_episode_count":2}],"id":66230}