{"vote_count":1670,"production_countries":[{"name":"United States of America","iso_3166_1":"US"}],"overview":"Le corps atrocement mutilé d'un garçon de onze ans est retrouvé dans une petite ville de l’Oklahoma. Les empreintes digitales et l’ADN présents sur les lieux du crime désignent aussitôt le coupable : Terry Maitland, l'un des habitants les plus respectés de la ville, entraîneur de l'équipe locale de baseball. L’affaire semble évidente à un détail près : Terry Maitland a un alibi en béton. Il était en effet à plusieurs centaines de kilomètres au moment où le meurtre a été commis. Le détective Ralph Anderson, proche de Maitland, est chargé de faire la lumière sur cette affaire pour le moins étrange. Et son explication pourrait bien dépasser l’entendement.","id":84661,"origin_country":["US"],"in_production":false,"languages":["en"],"next_episode_to_air":null,"softcore":false,"number_of_seasons":1,"genres":[{"id":18,"name":"Drame"},{"id":9648,"name":"Mystère"},{"id":80,"name":"Crime"}],"poster_path":"\/g2uOKfpQXb3y3eFTCyGmtcHRkVy.jpg","first_air_date":"2020-01-12","production_companies":[{"logo_path":"\/xpbUNXnrMeEK1ynbqVnHp8ZOVKW.png","id":37361,"origin_country":"US","name":"Aggregate Films"},{"logo_path":"\/5J93SHsuvIV32AE9oSbMi02pqw9.png","id":12292,"origin_country":"US","name":"Temple Hill Entertainment"},{"logo_path":"\/9MfCJ2G6Nrf9yyRj4tAgPmMiDcn.png","id":2531,"origin_country":"US","name":"MRC"},{"logo_path":null,"id":278874,"origin_country":"","name":"Pieface"},{"logo_path":null,"id":150893,"origin_country":"US","name":"Civic Center Media"}],"type":"Miniseries","spoken_languages":[{"english_name":"English","name":"English","iso_639_1":"en"}],"created_by":[{"gender":2,"id":2989,"profile_path":"\/nK2efymwH8qBPYR6YW7Nd0yyE9o.jpg","credit_id":"5e1be39e0e29a20015f6fcbf","original_name":"Richard Price","name":"Richard Price"}],"homepage":"https:\/\/www.hbo.com\/the-outsider","original_name":"The Outsider","name":"The Outsider","status":"Ended","tagline":"La peur a de nombreux visages.","number_of_episodes":10,"popularity":11.119,"backdrop_path":"\/lmlsqpAfDZnZumcFhbsTrOy9uNZ.jpg","last_episode_to_air":{"id":2008379,"production_code":"","season_number":1,"episode_number":10,"episode_type":"finale","runtime":60,"overview":"C'est une épreuve de force qui attend Holly, Ralph et consorts, qui mettent tout en oeuvre pour éradiquer El Cuco.","air_date":"2020-03-08","still_path":"\/r7QWJZ08IewtrVP1tes8WVNJZii.jpg","vote_count":36,"show_id":84661,"name":"Devoir mais ne pas pouvoir","vote_average":7},"seasons":[{"air_date":"2020-01-12","poster_path":"\/5SFJGSLMveSYCsHUqlmSFJLMK1b.jpg","id":113758,"season_number":1,"vote_average":7.5999999999999996,"episode_count":10,"name":"Saison 1","overview":""}],"original_language":"en","adult":false,"episode_run_time":[60],"last_air_date":"2020-03-08","networks":[{"logo_path":"\/tuomPhY2UtuPTqqFnKMVHvSb724.png","id":49,"origin_country":"US","name":"HBO"}],"vote_average":7.3600000000000003}