{"crew":[{"gender":1,"original_name":"Silver Tree","total_episode_count":1,"id":1169988,"adult":false,"known_for_department":"Directing","popularity":2.8740000000000001,"jobs":[{"credit_id":"65723109172d7f00eadcaea3","job":"Director","episode_count":1}],"department":"Directing","profile_path":"\/zVRj2hUcBCuWHQ6ZzFnMTUZkIbg.jpg","name":"Silver Tree"},{"gender":1,"original_name":"Silver Tree","total_episode_count":8,"id":1169988,"adult":false,"known_for_department":"Directing","popularity":2.8740000000000001,"jobs":[{"credit_id":"657230f86dc6c0013b41ae87","job":"Executive Producer","episode_count":8}],"department":"Production","profile_path":"\/zVRj2hUcBCuWHQ6ZzFnMTUZkIbg.jpg","name":"Silver Tree"},{"gender":2,"original_name":"Will Ferrell","total_episode_count":8,"id":23659,"adult":false,"known_for_department":"Acting","popularity":27.167000000000002,"jobs":[{"credit_id":"657230cc65686e01014c7a46","job":"Executive Producer","episode_count":8}],"department":"Production","profile_path":"\/xYPM1OOLXZguj4FsgmOzTSUXaXd.jpg","name":"Will Ferrell"},{"gender":1,"original_name":"Liz Feldman","total_episode_count":8,"id":1218684,"adult":false,"known_for_department":"Production","popularity":2.2770000000000001,"jobs":[{"credit_id":"657230bfb6cff100ff1b2a66","job":"Executive Producer","episode_count":8}],"department":"Production","profile_path":"\/8luIoDA2x31sXfb4tU6FFCVko4B.jpg","name":"Liz Feldman"},{"gender":1,"original_name":"Jessica Elbaum","total_episode_count":8,"id":80175,"adult":false,"known_for_department":"Production","popularity":2.9740000000000002,"jobs":[{"credit_id":"657230d935c30a00eb37f079","job":"Executive Producer","episode_count":8}],"department":"Production","profile_path":null,"name":"Jessica Elbaum"},{"gender":0,"original_name":"Christie Smith","total_episode_count":8,"id":2303399,"adult":false,"known_for_department":"Production","popularity":0.001,"jobs":[{"credit_id":"657230e935c30a014ecada00","job":"Executive Producer","episode_count":8}],"department":"Production","profile_path":null,"name":"Christie Smith"},{"gender":1,"original_name":"Sherry Thomas","total_episode_count":8,"id":959387,"adult":false,"known_for_department":"Production","popularity":2.0840000000000001,"jobs":[{"credit_id":"657231446c8492012ccf0905","job":"Casting","episode_count":8}],"department":"Production","profile_path":null,"name":"Sherry Thomas"},{"gender":2,"original_name":"Russell Scott","total_episode_count":8,"id":1537675,"adult":false,"known_for_department":"Production","popularity":0.50700000000000001,"jobs":[{"credit_id":"65723150b6cff100c5bc961b","job":"Casting","episode_count":8}],"department":"Production","profile_path":null,"name":"Russell Scott"}],"cast":[{"gender":2,"original_name":"Ray Romano","roles":[{"credit_id":"6572309f4b0c6300e321416b","character":"Paul Morgan","episode_count":8}],"id":15757,"adult":false,"known_for_department":"Acting","popularity":25.43,"order":0,"profile_path":"\/zWT03QvuVYySlrjmHCojKrNYjoC.jpg","name":"Ray Romano","total_episode_count":8},{"gender":1,"original_name":"Lisa Kudrow","roles":[{"credit_id":"657bbf31564ec700e10e2c41","character":"Lydia Morgan","episode_count":8}],"id":14406,"adult":false,"known_for_department":"Acting","popularity":29.326000000000001,"order":1,"profile_path":"\/dWoXQonmmtV1byxmKXCd8E4rlPC.jpg","name":"Lisa Kudrow","total_episode_count":8},{"gender":1,"original_name":"Linda Cardellini","roles":[{"credit_id":"657ca1fa7a3c52012d0260df","character":"Margo Starling","episode_count":8}],"id":1817,"adult":false,"known_for_department":"Acting","popularity":48.146999999999998,"order":2,"profile_path":"\/usfaqDAw9o6JgSGo95WdNzHWQSm.jpg","name":"Linda Cardellini","total_episode_count":8},{"gender":1,"original_name":"Abbi Jacobson","roles":[{"credit_id":"657ca202e93e9521900e56ef","character":"Leslie Fisher","episode_count":8}],"id":1325731,"adult":false,"known_for_department":"Acting","popularity":7.7439999999999998,"order":3,"profile_path":"\/tYTlv2MmiOjPfkOE9ywGAaqllbv.jpg","name":"Abbi Jacobson","total_episode_count":8},{"gender":2,"original_name":"Luke Wilson","roles":[{"credit_id":"657ca20b8e2ba600ac8daa48","character":"JD Campbell","episode_count":8}],"id":36422,"adult":false,"known_for_department":"Acting","popularity":17.628,"order":4,"profile_path":"\/nH1h9dZGSBuWIOyX27HpYyYykvr.jpg","name":"Luke Wilson","total_episode_count":8},{"gender":1,"original_name":"Teyonah Parris","roles":[{"credit_id":"657ca21ae93e952192cdeb2a","character":"Carla","episode_count":8}],"id":970219,"adult":false,"known_for_department":"Acting","popularity":12.534000000000001,"order":5,"profile_path":"\/mArqi5mGbKvfrNsrEEkdy0gDvGu.jpg","name":"Teyonah Parris","total_episode_count":8},{"gender":1,"original_name":"Poppy Liu","roles":[{"credit_id":"657ca224ec8a4300aa6e3e37","character":"Sarah","episode_count":8}],"id":2392602,"adult":false,"known_for_department":"Acting","popularity":4.8490000000000002,"order":6,"profile_path":"\/i36QkUChZN7K8BQa1ReaZHes6L4.jpg","name":"Poppy Liu","total_episode_count":8},{"gender":2,"original_name":"Denis Leary","roles":[{"credit_id":"659daab91d356300eee9287e","character":"Mikey","episode_count":8}],"id":5724,"adult":false,"known_for_department":"Acting","popularity":19.556999999999999,"order":7,"profile_path":"\/nAqHuIw8z1QodcXdaJQShKogVFa.jpg","name":"Denis Leary","total_episode_count":8},{"gender":2,"original_name":"O-T Fagbenle","roles":[{"credit_id":"659daac09bcd0f009463fd7d","character":"Dennis","episode_count":8}],"id":113970,"adult":false,"known_for_department":"Acting","popularity":8.1590000000000007,"order":8,"profile_path":"\/baIiZBDYpYXfG4SlonbcqyYg6l.jpg","name":"O-T Fagbenle","total_episode_count":8},{"gender":2,"original_name":"Matt Rogers","roles":[{"credit_id":"65c53b8f2efe4e0162518713","character":"Greg","episode_count":8}],"id":1429585,"adult":false,"known_for_department":"Acting","popularity":4.157,"order":9,"profile_path":"\/e1o0DW1pmWcDFBKO3IJPnVg7hnG.jpg","name":"Matt Rogers","total_episode_count":8},{"gender":1,"original_name":"Anna Maria Horsford","roles":[{"credit_id":"65c53b9c1c6aa7014a9930ef","character":"Denise","episode_count":8}],"id":54800,"adult":false,"known_for_department":"Acting","popularity":10.215999999999999,"order":10,"profile_path":"\/fVA25hLtwmrVsIVrcWOojaPoYEq.jpg","name":"Anna Maria Horsford","total_episode_count":8},{"gender":1,"original_name":"Katherine Moennig","roles":[{"credit_id":"65c53bb3aa659e0164ed8246","character":"Gwen","episode_count":8}],"id":122231,"adult":false,"known_for_department":"Acting","popularity":17.742999999999999,"order":11,"profile_path":"\/k9V8rcebmJlbfePAigJWG7yWaW5.jpg","name":"Katherine Moennig","total_episode_count":8},{"gender":1,"original_name":"Linda Lavin","roles":[{"credit_id":"65c53bc01b70ae0163a22620","character":"Phyllis","episode_count":8}],"id":113223,"adult":false,"known_for_department":"Acting","popularity":11.44,"order":12,"profile_path":"\/tHaiiQH5UKVA5fGbjzwe6hh1Rwc.jpg","name":"Linda Lavin","total_episode_count":8},{"gender":2,"original_name":"Wyatt Aubrey","roles":[{"credit_id":"65c53c3aaa659e017ded961f","character":"Jacob","episode_count":8}],"id":4525635,"adult":false,"known_for_department":"Acting","popularity":0.001,"order":13,"profile_path":null,"name":"Wyatt Aubrey","total_episode_count":8}],"id":241112}