{"runtime":100,"status":"Released","backdrop_path":"\/fOy2Jurz9k6RnJnMUMRDAgBwru2.jpg","overview":"Les aventures de Meilin Lee, une jeune adolescente de 13 ans, pleine d’assurance, mais tiraillée entre son image de petite fille modèle aux yeux de sa mère hyper protectrice et le chaos de l’adolescence. Et comme si tous les changements qui s’opèrent en elle ne suffisaient pas, chaque fois qu’elle est débordée par ses émotions - ce qui, pour une ado, arrive quasiment tout le temps - elle se transforme en panda roux géant !","title":"Alerte rouge","vote_count":3515,"tagline":"Bienvenue dans l'âge bête.","belongs_to_collection":null,"original_title":"Turning Red","original_language":"en","poster_path":"\/jBCUJ90BVXIDSLlXUvgQcj6LOHa.jpg","production_countries":[{"name":"United States of America","iso_3166_1":"US"}],"revenue":18879922,"homepage":"https:\/\/disney.fr\/films\/alerte-rouge","video":false,"imdb_id":"tt8097030","id":508947,"release_date":"2022-03-01","budget":190000000,"popularity":624.29499999999996,"genres":[{"id":16,"name":"Animation"},{"id":10751,"name":"Familial"},{"id":35,"name":"Comédie"},{"id":14,"name":"Fantastique"}],"production_companies":[{"logo_path":"\/wdrCwmRnLFJhEoH8GSfymY85KHT.png","id":2,"origin_country":"US","name":"Walt Disney Pictures"},{"logo_path":"\/1TjvGVDMYsj6JBxOAkUHpPEwLf7.png","id":3,"origin_country":"US","name":"Pixar"}],"adult":false,"spoken_languages":[{"english_name":"Cantonese","name":"广州话 \/ 廣州話","iso_639_1":"cn"},{"english_name":"Mandarin","name":"普通话","iso_639_1":"zh"},{"english_name":"Korean","name":"한국어\/조선말","iso_639_1":"ko"},{"english_name":"English","name":"English","iso_639_1":"en"},{"english_name":"French","name":"Français","iso_639_1":"fr"}],"vote_average":7.5170000000000003}